extended_a2a/__init__.py
extended_a2a/auth_plugin.py
extended_a2a/types.py
extended_a2a-0.1.0.dist-info/METADATA
extended_a2a-0.1.0.dist-info/WHEEL
extended_a2a-0.1.0.dist-info/RECORD
